sais_prism/__init__.py
sais_prism/__pycache__/__init__.cpython-311.pyc
sais_prism/core/config.py
sais_prism/core/decorators.py
sais_prism/core/exceptions.py
sais_prism/core/service_locator.py
sais_prism/core/__pycache__/config.cpython-311.pyc
sais_prism/core/__pycache__/decorators.cpython-311.pyc
sais_prism/core/__pycache__/exceptions.cpython-311.pyc
sais_prism/core/__pycache__/service_locator.cpython-311.pyc
sais_prism/ml/mlflow_integration.py
sais_prism/ml/__pycache__/mlflow_integration.cpython-311.pyc
sais_prism/unified_data_access/client.py
sais_prism/unified_data_access/__pycache__/client.cpython-311.pyc
sais_prism_sdk-0.1.0b13.dist-info/licenses/LICENSE
sais_prism_sdk-0.1.0b13.dist-info/METADATA
sais_prism_sdk-0.1.0b13.dist-info/WHEEL
sais_prism_sdk-0.1.0b13.dist-info/top_level.txt
sais_prism_sdk-0.1.0b13.dist-info/RECORD
