Metadata-Version: 2.4
Name: sais-prism-sdk
Version: 0.1.0b13
Summary: SAIS Prism: A unified interface for ML data access and lifecycle management
Home-page: http://gitlab-paas.internal.sais.com.cn/data_intelligence_platform/sais-prism
Author: Shepard
Author-email: Shepard <zhaoxun@sais.com.cn>
License: The Unlicense
Requires-Python: >=3.10
License-File: LICENSE
Requires-Dist: mlflow>=2.0.0
Requires-Dist: PyYAML>=6.0
Requires-Dist: scikit-learn>=1.2.0
Requires-Dist: transformers>=4.30.0
Requires-Dist: torch>=2.0.0
Requires-Dist: peft>=0.4.0
Requires-Dist: psutil
Requires-Dist: pynvml
Dynamic: author
Dynamic: home-page
Dynamic: license-file
Dynamic: requires-python
